configs/__init__.py
configs/camera.yaml
examples/__init__.py
examples/line_follow.py
examples/line_sensor.py
examples/motors/__init__.py
examples/motors/motor_duty.py
examples/motors/motor_wheel_control.py
fast_sdk/__init__.py
fast_sdk/board_sdk.py
fast_sdk/infra_red.py
fast_sdk/line_follower.py
fast_sdk/motors.py
fast_sdk/utils/__init__.py
fast_sdk/utils/check_sum.py
fast_sdk/utils/functions.py
fast_sdk/utils/pid_controller.py
tests/__init__.py
turbopi_fast_sdk-0.3.6.dist-info/LICENSE
turbopi_fast_sdk-0.3.6.dist-info/METADATA
turbopi_fast_sdk-0.3.6.dist-info/WHEEL
turbopi_fast_sdk-0.3.6.dist-info/RECORD
