Metadata-Version: 2.3
Name: turbopi-fast-sdk
Version: 0.3.6
Summary: Python SDK for hiwonder TurboPi device communication
License: MIT
Keywords: SDK,TurboPi,Python,Hiwonder
Author: Dmytro Berezovskyi
Author-email: dmberezovskyi@gmail.com
Requires-Python: >=3.11
Classifier: License :: OSI Approved :: MIT License
Classifier: Programming Language :: Python :: 3
Classifier: Programming Language :: Python :: 3.11
Classifier: Programming Language :: Python :: 3.12
Classifier: Programming Language :: Python :: 3.13
Requires-Dist: pyserial (>=3.5,<4.0)
Requires-Dist: pytest (>=8.3,<9.0)
Requires-Dist: requests (>=2.31,<3.0)
Requires-Dist: smbus2 (>=0.5.0,<0.6.0)
Project-URL: Repository, https://github.com/dmberezovskyii/fast-hiwonder
